{
  "version": 1.0,
  "cardVariants": [
    "core",
    "reverse"
  ],
  "coreCards": [
    {
      "id": "sm3-1",
      "rarity": "Common",
      "name": "Caterpie",
      "number": "1"
    },
    {
      "id": "sm3-2",
      "rarity": "Uncommon",
      "name": "Metapod",
      "number": "2"
    },
    {
      "id": "sm3-3",
      "rarity": "Rare",
      "name": "Butterfree",
      "number": "3"
    },
    {
      "id": "sm3-4",
      "rarity": "Common",
      "name": "Oddish",
      "number": "4"
    },
    {
      "id": "sm3-5",
      "rarity": "Uncommon",
      "name": "Gloom",
      "number": "5"
    },
    {
      "id": "sm3-6",
      "rarity": "Rare Holo",
      "name": "Vileplume",
      "number": "6"
    },
    {
      "id": "sm3-7",
      "rarity": "Common",
      "name": "Tangela",
      "number": "7"
    },
    {
      "id": "sm3-8",
      "rarity": "Rare",
      "name": "Tangrowth",
      "number": "8"
    },
    {
      "id": "sm3-9",
      "rarity": "Common",
      "name": "Ledyba",
      "number": "9"
    },
    {
      "id": "sm3-10",
      "rarity": "Rare",
      "name": "Ledian",
      "number": "10"
    },
    {
      "id": "sm3-11",
      "rarity": "Rare",
      "name": "Heracross",
      "number": "11"
    },
    {
      "id": "sm3-12",
      "rarity": "Common",
      "name": "Pansage",
      "number": "12"
    },
    {
      "id": "sm3-13",
      "rarity": "Uncommon",
      "name": "Simisage",
      "number": "13"
    },
    {
      "id": "sm3-14",
      "rarity": "Common",
      "name": "Dewpider",
      "number": "14"
    },
    {
      "id": "sm3-15",
      "rarity": "Rare",
      "name": "Araquanid",
      "number": "15"
    },
    {
      "id": "sm3-16",
      "rarity": "Common",
      "name": "Wimpod",
      "number": "16"
    },
    {
      "id": "sm3-17",
      "rarity": "Rare Holo GX",
      "name": "Golisopod-GX",
      "number": "17"
    },
    {
      "id": "sm3-18",
      "rarity": "Common",
      "name": "Charmander",
      "number": "18"
    },
    {
      "id": "sm3-19",
      "rarity": "Uncommon",
      "name": "Charmeleon",
      "number": "19"
    },
    {
      "id": "sm3-20",
      "rarity": "Rare Holo GX",
      "name": "Charizard-GX",
      "number": "20"
    },
    {
      "id": "sm3-21",
      "rarity": "Rare Holo GX",
      "name": "Ho-Oh-GX",
      "number": "21"
    },
    {
      "id": "sm3-22",
      "rarity": "Common",
      "name": "Pansear",
      "number": "22"
    },
    {
      "id": "sm3-23",
      "rarity": "Uncommon",
      "name": "Simisear",
      "number": "23"
    },
    {
      "id": "sm3-24",
      "rarity": "Uncommon",
      "name": "Heatmor",
      "number": "24"
    },
    {
      "id": "sm3-25",
      "rarity": "Rare Holo GX",
      "name": "Salazzle-GX",
      "number": "25"
    },
    {
      "id": "sm3-26",
      "rarity": "Rare",
      "name": "Turtonator",
      "number": "26"
    },
    {
      "id": "sm3-27",
      "rarity": "Common",
      "name": "Alolan Vulpix",
      "number": "27"
    },
    {
      "id": "sm3-28",
      "rarity": "Rare",
      "name": "Alolan Ninetales",
      "number": "28"
    },
    {
      "id": "sm3-29",
      "rarity": "Common",
      "name": "Horsea",
      "number": "29"
    },
    {
      "id": "sm3-30",
      "rarity": "Uncommon",
      "name": "Seadra",
      "number": "30"
    },
    {
      "id": "sm3-31",
      "rarity": "Rare Holo",
      "name": "Kingdra",
      "number": "31"
    },
    {
      "id": "sm3-32",
      "rarity": "Common",
      "name": "Magikarp",
      "number": "32"
    },
    {
      "id": "sm3-33",
      "rarity": "Rare Holo",
      "name": "Gyarados",
      "number": "33"
    },
    {
      "id": "sm3-34",
      "rarity": "Common",
      "name": "Marill",
      "number": "34"
    },
    {
      "id": "sm3-35",
      "rarity": "Rare",
      "name": "Azumarill",
      "number": "35"
    },
    {
      "id": "sm3-36",
      "rarity": "Common",
      "name": "Panpour",
      "number": "36"
    },
    {
      "id": "sm3-37",
      "rarity": "Uncommon",
      "name": "Simipour",
      "number": "37"
    },
    {
      "id": "sm3-38",
      "rarity": "Rare",
      "name": "Bruxish",
      "number": "38"
    },
    {
      "id": "sm3-39",
      "rarity": "Rare Holo GX",
      "name": "Tapu Fini-GX",
      "number": "39"
    },
    {
      "id": "sm3-40",
      "rarity": "Common",
      "name": "Pikachu",
      "number": "40"
    },
    {
      "id": "sm3-41",
      "rarity": "Rare Holo",
      "name": "Raichu",
      "number": "41"
    },
    {
      "id": "sm3-42",
      "rarity": "Uncommon",
      "name": "Electabuzz",
      "number": "42"
    },
    {
      "id": "sm3-43",
      "rarity": "Rare",
      "name": "Electivire",
      "number": "43"
    },
    {
      "id": "sm3-44",
      "rarity": "Common",
      "name": "Tynamo",
      "number": "44"
    },
    {
      "id": "sm3-45",
      "rarity": "Uncommon",
      "name": "Eelektrik",
      "number": "45"
    },
    {
      "id": "sm3-46",
      "rarity": "Rare",
      "name": "Eelektross",
      "number": "46"
    },
    {
      "id": "sm3-47",
      "rarity": "Common",
      "name": "Togedemaru",
      "number": "47"
    },
    {
      "id": "sm3-48",
      "rarity": "Rare",
      "name": "Slowking",
      "number": "48"
    },
    {
      "id": "sm3-49",
      "rarity": "Uncommon",
      "name": "Wobbuffet",
      "number": "49"
    },
    {
      "id": "sm3-50",
      "rarity": "Uncommon",
      "name": "Seviper",
      "number": "50"
    },
    {
      "id": "sm3-51",
      "rarity": "Common",
      "name": "Duskull",
      "number": "51"
    },
    {
      "id": "sm3-52",
      "rarity": "Uncommon",
      "name": "Dusclops",
      "number": "52"
    },
    {
      "id": "sm3-53",
      "rarity": "Rare Holo",
      "name": "Dusknoir",
      "number": "53"
    },
    {
      "id": "sm3-54",
      "rarity": "Common",
      "name": "Croagunk",
      "number": "54"
    },
    {
      "id": "sm3-55",
      "rarity": "Rare",
      "name": "Toxicroak",
      "number": "55"
    },
    {
      "id": "sm3-56",
      "rarity": "Common",
      "name": "Venipede",
      "number": "56"
    },
    {
      "id": "sm3-57",
      "rarity": "Uncommon",
      "name": "Whirlipede",
      "number": "57"
    },
    {
      "id": "sm3-58",
      "rarity": "Rare",
      "name": "Scolipede",
      "number": "58"
    },
    {
      "id": "sm3-59",
      "rarity": "Common",
      "name": "Espurr",
      "number": "59"
    },
    {
      "id": "sm3-60",
      "rarity": "Rare",
      "name": "Meowstic",
      "number": "60"
    },
    {
      "id": "sm3-61",
      "rarity": "Common",
      "name": "Sandygast",
      "number": "61"
    },
    {
      "id": "sm3-62",
      "rarity": "Rare Holo",
      "name": "Palossand",
      "number": "62"
    },
    {
      "id": "sm3-63",
      "rarity": "Rare Holo GX",
      "name": "Necrozma-GX",
      "number": "63"
    },
    {
      "id": "sm3-64",
      "rarity": "Rare Holo GX",
      "name": "Machamp-GX",
      "number": "64"
    },
    {
      "id": "sm3-65",
      "rarity": "Common",
      "name": "Rhyhorn",
      "number": "65"
    },
    {
      "id": "sm3-66",
      "rarity": "Uncommon",
      "name": "Rhydon",
      "number": "66"
    },
    {
      "id": "sm3-67",
      "rarity": "Rare Holo",
      "name": "Rhyperior",
      "number": "67"
    },
    {
      "id": "sm3-68",
      "rarity": "Uncommon",
      "name": "Lunatone",
      "number": "68"
    },
    {
      "id": "sm3-69",
      "rarity": "Uncommon",
      "name": "Solrock",
      "number": "69"
    },
    {
      "id": "sm3-70",
      "rarity": "Common",
      "name": "Riolu",
      "number": "70"
    },
    {
      "id": "sm3-71",
      "rarity": "Rare Holo",
      "name": "Lucario",
      "number": "71"
    },
    {
      "id": "sm3-72",
      "rarity": "Common",
      "name": "Sawk",
      "number": "72"
    },
    {
      "id": "sm3-73",
      "rarity": "Common",
      "name": "Crabrawler",
      "number": "73"
    },
    {
      "id": "sm3-74",
      "rarity": "Rare",
      "name": "Crabominable",
      "number": "74"
    },
    {
      "id": "sm3-75",
      "rarity": "Rare Holo",
      "name": "Lycanroc",
      "number": "75"
    },
    {
      "id": "sm3-76",
      "rarity": "Rare",
      "name": "Lycanroc",
      "number": "76"
    },
    {
      "id": "sm3-77",
      "rarity": "Common",
      "name": "Mudbray",
      "number": "77"
    },
    {
      "id": "sm3-78",
      "rarity": "Rare",
      "name": "Mudsdale",
      "number": "78"
    },
    {
      "id": "sm3-79",
      "rarity": "Rare",
      "name": "Passimian",
      "number": "79"
    },
    {
      "id": "sm3-80",
      "rarity": "Rare Holo GX",
      "name": "Marshadow-GX",
      "number": "80"
    },
    {
      "id": "sm3-81",
      "rarity": "Common",
      "name": "Alolan Rattata",
      "number": "81"
    },
    {
      "id": "sm3-82",
      "rarity": "Rare",
      "name": "Alolan Raticate",
      "number": "82"
    },
    {
      "id": "sm3-83",
      "rarity": "Common",
      "name": "Alolan Grimer",
      "number": "83"
    },
    {
      "id": "sm3-84",
      "rarity": "Rare Holo GX",
      "name": "Alolan Muk-GX",
      "number": "84"
    },
    {
      "id": "sm3-85",
      "rarity": "Common",
      "name": "Sneasel",
      "number": "85"
    },
    {
      "id": "sm3-86",
      "rarity": "Rare",
      "name": "Weavile",
      "number": "86"
    },
    {
      "id": "sm3-87",
      "rarity": "Rare Holo",
      "name": "Darkrai",
      "number": "87"
    },
    {
      "id": "sm3-88",
      "rarity": "Rare Holo GX",
      "name": "Darkrai-GX",
      "number": "88"
    },
    {
      "id": "sm3-89",
      "rarity": "Common",
      "name": "Inkay",
      "number": "89"
    },
    {
      "id": "sm3-90",
      "rarity": "Rare",
      "name": "Malamar",
      "number": "90"
    },
    {
      "id": "sm3-91",
      "rarity": "Common",
      "name": "Ralts",
      "number": "91"
    },
    {
      "id": "sm3-92",
      "rarity": "Uncommon",
      "name": "Kirlia",
      "number": "92"
    },
    {
      "id": "sm3-93",
      "rarity": "Rare Holo GX",
      "name": "Gardevoir-GX",
      "number": "93"
    },
    {
      "id": "sm3-94",
      "rarity": "Rare Holo",
      "name": "Diancie",
      "number": "94"
    },
    {
      "id": "sm3-95",
      "rarity": "Common",
      "name": "Cutiefly",
      "number": "95"
    },
    {
      "id": "sm3-96",
      "rarity": "Uncommon",
      "name": "Ribombee",
      "number": "96"
    },
    {
      "id": "sm3-97",
      "rarity": "Common",
      "name": "Morelull",
      "number": "97"
    },
    {
      "id": "sm3-98",
      "rarity": "Rare",
      "name": "Shiinotic",
      "number": "98"
    },
    {
      "id": "sm3-99",
      "rarity": "Rare Holo GX",
      "name": "Noivern-GX",
      "number": "99"
    },
    {
      "id": "sm3-100",
      "rarity": "Rare Holo",
      "name": "Zygarde",
      "number": "100"
    },
    {
      "id": "sm3-101",
      "rarity": "Common",
      "name": "Meowth",
      "number": "101"
    },
    {
      "id": "sm3-102",
      "rarity": "Rare",
      "name": "Persian",
      "number": "102"
    },
    {
      "id": "sm3-103",
      "rarity": "Common",
      "name": "Porygon",
      "number": "103"
    },
    {
      "id": "sm3-104",
      "rarity": "Uncommon",
      "name": "Porygon2",
      "number": "104"
    },
    {
      "id": "sm3-105",
      "rarity": "Rare Holo",
      "name": "Porygon-Z",
      "number": "105"
    },
    {
      "id": "sm3-106",
      "rarity": "Common",
      "name": "Hoothoot",
      "number": "106"
    },
    {
      "id": "sm3-107",
      "rarity": "Uncommon",
      "name": "Noctowl",
      "number": "107"
    },
    {
      "id": "sm3-108",
      "rarity": "Uncommon",
      "name": "Bouffalant",
      "number": "108"
    },
    {
      "id": "sm3-109",
      "rarity": "Common",
      "name": "Noibat",
      "number": "109"
    },
    {
      "id": "sm3-110",
      "rarity": "Common",
      "name": "Stufful",
      "number": "110"
    },
    {
      "id": "sm3-111",
      "rarity": "Rare",
      "name": "Bewear",
      "number": "111"
    },
    {
      "id": "sm3-112",
      "rarity": "Uncommon",
      "name": "Acerola",
      "number": "112"
    },
    {
      "id": "sm3-113",
      "rarity": "Uncommon",
      "name": "Bodybuilding Dumbbells",
      "number": "113"
    },
    {
      "id": "sm3-114",
      "rarity": "Uncommon",
      "name": "Escape Rope",
      "number": "114"
    },
    {
      "id": "sm3-115",
      "rarity": "Uncommon",
      "name": "Guzma",
      "number": "115"
    },
    {
      "id": "sm3-116",
      "rarity": "Uncommon",
      "name": "Kiawe",
      "number": "116"
    },
    {
      "id": "sm3-117",
      "rarity": "Uncommon",
      "name": "Lana",
      "number": "117"
    },
    {
      "id": "sm3-118",
      "rarity": "Uncommon",
      "name": "Mount Lanakila",
      "number": "118"
    },
    {
      "id": "sm3-119",
      "rarity": "Uncommon",
      "name": "Olivia",
      "number": "119"
    },
    {
      "id": "sm3-120",
      "rarity": "Uncommon",
      "name": "Plumeria",
      "number": "120"
    },
    {
      "id": "sm3-121",
      "rarity": "Uncommon",
      "name": "Po Town",
      "number": "121"
    },
    {
      "id": "sm3-122",
      "rarity": "Uncommon",
      "name": "Rotom Dex\u2014Pok\u00e9 Finder Mode",
      "number": "122"
    },
    {
      "id": "sm3-123",
      "rarity": "Uncommon",
      "name": "Sophocles",
      "number": "123"
    },
    {
      "id": "sm3-124",
      "rarity": "Uncommon",
      "name": "Super Scoop Up",
      "number": "124"
    },
    {
      "id": "sm3-125",
      "rarity": "Uncommon",
      "name": "Tormenting Spray",
      "number": "125"
    },
    {
      "id": "sm3-126",
      "rarity": "Uncommon",
      "name": "Weakness Policy",
      "number": "126"
    },
    {
      "id": "sm3-127",
      "rarity": "Uncommon",
      "name": "Wicke",
      "number": "127"
    },
    {
      "id": "sm3-128",
      "rarity": "Uncommon",
      "name": "Wishful Baton",
      "number": "128"
    },
    {
      "id": "sm3-129",
      "rarity": "Rare Ultra",
      "name": "Golisopod-GX",
      "number": "129"
    },
    {
      "id": "sm3-130",
      "rarity": "Rare Ultra",
      "name": "Tapu Bulu-GX",
      "number": "130"
    },
    {
      "id": "sm3-131",
      "rarity": "Rare Ultra",
      "name": "Ho-Oh-GX",
      "number": "131"
    },
    {
      "id": "sm3-132",
      "rarity": "Rare Ultra",
      "name": "Salazzle-GX",
      "number": "132"
    },
    {
      "id": "sm3-133",
      "rarity": "Rare Ultra",
      "name": "Tapu Fini-GX",
      "number": "133"
    },
    {
      "id": "sm3-134",
      "rarity": "Rare Ultra",
      "name": "Necrozma-GX",
      "number": "134"
    },
    {
      "id": "sm3-135",
      "rarity": "Rare Ultra",
      "name": "Machamp-GX",
      "number": "135"
    },
    {
      "id": "sm3-136",
      "rarity": "Rare Ultra",
      "name": "Lycanroc-GX",
      "number": "136"
    },
    {
      "id": "sm3-137",
      "rarity": "Rare Ultra",
      "name": "Marshadow-GX",
      "number": "137"
    },
    {
      "id": "sm3-138",
      "rarity": "Rare Ultra",
      "name": "Alolan Muk-GX",
      "number": "138"
    },
    {
      "id": "sm3-139",
      "rarity": "Rare Ultra",
      "name": "Darkrai-GX",
      "number": "139"
    },
    {
      "id": "sm3-140",
      "rarity": "Rare Ultra",
      "name": "Gardevoir-GX",
      "number": "140"
    },
    {
      "id": "sm3-141",
      "rarity": "Rare Ultra",
      "name": "Noivern-GX",
      "number": "141"
    },
    {
      "id": "sm3-142",
      "rarity": "Rare Ultra",
      "name": "Acerola",
      "number": "142"
    },
    {
      "id": "sm3-143",
      "rarity": "Rare Ultra",
      "name": "Guzma",
      "number": "143"
    },
    {
      "id": "sm3-144",
      "rarity": "Rare Ultra",
      "name": "Kiawe",
      "number": "144"
    },
    {
      "id": "sm3-145",
      "rarity": "Rare Ultra",
      "name": "Plumeria",
      "number": "145"
    },
    {
      "id": "sm3-146",
      "rarity": "Rare Ultra",
      "name": "Sophocles",
      "number": "146"
    },
    {
      "id": "sm3-147",
      "rarity": "Rare Ultra",
      "name": "Wicke",
      "number": "147"
    },
    {
      "id": "sm3-148",
      "rarity": "Rare Secret",
      "name": "Golisopod-GX",
      "number": "148"
    },
    {
      "id": "sm3-149",
      "rarity": "Rare Secret",
      "name": "Tapu Bulu-GX",
      "number": "149"
    },
    {
      "id": "sm3-150",
      "rarity": "Rare Secret",
      "name": "Charizard GX",
      "number": "150"
    },
    {
      "id": "sm3-151",
      "rarity": "Rare Secret",
      "name": "Salazzle-GX",
      "number": "151"
    },
    {
      "id": "sm3-152",
      "rarity": "Rare Secret",
      "name": "Tapu Fini-GX",
      "number": "152"
    },
    {
      "id": "sm3-153",
      "rarity": "Rare Secret",
      "name": "Necrozma-GX",
      "number": "153"
    },
    {
      "id": "sm3-154",
      "rarity": "Rare Secret",
      "name": "Machamp-GX",
      "number": "154"
    },
    {
      "id": "sm3-155",
      "rarity": "Rare Secret",
      "name": "Lycanroc-GX",
      "number": "155"
    },
    {
      "id": "sm3-156",
      "rarity": "Rare Secret",
      "name": "Marshadow-GX",
      "number": "156"
    },
    {
      "id": "sm3-157",
      "rarity": "Rare Secret",
      "name": "Alolan Muk-GX",
      "number": "157"
    },
    {
      "id": "sm3-158",
      "rarity": "Rare Secret",
      "name": "Darkrai-GX",
      "number": "158"
    },
    {
      "id": "sm3-159",
      "rarity": "Rare Secret",
      "name": "Gardevoir-GX",
      "number": "159"
    },
    {
      "id": "sm3-160",
      "rarity": "Rare Secret",
      "name": "Noivern-GX",
      "number": "160"
    },
    {
      "id": "sm3-161",
      "rarity": "Rare Secret",
      "name": "Bodybuilding Dumbbells",
      "number": "161"
    },
    {
      "id": "sm3-162",
      "rarity": "Rare Secret",
      "name": "Choice Band",
      "number": "162"
    },
    {
      "id": "sm3-163",
      "rarity": "Rare Secret",
      "name": "Escape Rope",
      "number": "163"
    },
    {
      "id": "sm3-164",
      "rarity": "Rare Secret",
      "name": "Multi Switch",
      "number": "164"
    },
    {
      "id": "sm3-165",
      "rarity": "Rare Secret",
      "name": "Rescue Stretcher",
      "number": "165"
    },
    {
      "id": "sm3-166",
      "rarity": "Rare Secret",
      "name": "Super Scoop Up",
      "number": "166"
    },
    {
      "id": "sm3-167",
      "rarity": "Rare Secret",
      "name": "Fire Energy",
      "number": "167"
    },
    {
      "id": "sm3-168",
      "rarity": "Rare Secret",
      "name": "Darkness Energy",
      "number": "168"
    },
    {
      "id": "sm3-169",
      "rarity": "Rare Secret",
      "name": "Fairy Energy",
      "number": "169"
    }
  ],
  "additionalCards": [],
  "other": []
}
